masterpiece_influx/__init__.py
masterpiece_influx/influx.py
masterpiece_influx/influx_measurement.py
masterpiece_influx/py.typed
masterpiece_influx-0.1.13.dist-info/licenses/LICENSE.rst
masterpiece_influx-0.1.13.dist-info/METADATA
masterpiece_influx-0.1.13.dist-info/WHEEL
masterpiece_influx-0.1.13.dist-info/entry_points.txt
masterpiece_influx-0.1.13.dist-info/top_level.txt
masterpiece_influx-0.1.13.dist-info/RECORD
